freecap/__init__.py
freecap_client-1.0.2.dist-info/licenses/LICENSE.md
freecap_client-1.0.2.dist-info/METADATA
freecap_client-1.0.2.dist-info/WHEEL
freecap_client-1.0.2.dist-info/top_level.txt
freecap_client-1.0.2.dist-info/RECORD
