Metadata-Version: 2.4
Name: freecap-client
Version: 1.0.2
Summary: A robust, production-ready async client for the FreeCap captcha solving service
Home-page: https://github.com/freecap-su/Wrappers
Author: FreeCap Client
Author-email: FreeCap Client <support@freecap.su>
License: GPL-3.0
Project-URL: Homepage, https://freecap.su
Project-URL: Documentation, https://freecap.su/docs
Project-URL: Repository, https://github.com/freecap-su/Wrappers
Project-URL: Bug Reports, https://github.com/freecap-su/Wrappers/issues
Keywords: captcha,hcaptcha,funcaptcha,geetest,automation,async,api-client
Classifier: Development Status :: 5 - Production/Stable
Classifier: Intended Audience :: Developers
Classifier: Topic :: Software Development :: Libraries :: Python Modules
Classifier: Topic :: Internet :: WWW/HTTP
Classifier: Topic :: Security
Classifier: License :: OSI Approved :: GNU General Public License v3 (GPLv3)
Classifier: Programming Language :: Python :: 3
Classifier: Programming Language :: Python :: 3.10
Classifier: Programming Language :: Python :: 3.11
Classifier: Programming Language :: Python :: 3.12
Classifier: Operating System :: OS Independent
Requires-Python: >=3.10
License-File: LICENSE.md
Requires-Dist: aiohttp>=3.12.15
Provides-Extra: dev
Requires-Dist: pytest>=8.4.2; extra == "dev"
Requires-Dist: pytest-asyncio>=1.2.0; extra == "dev"
Requires-Dist: black>=25.9.0; extra == "dev"
Requires-Dist: flake8>=7.3.0; extra == "dev"
Requires-Dist: mypy>=1.18.2; extra == "dev"
Dynamic: author
Dynamic: home-page
Dynamic: license-file
Dynamic: requires-python
